Metadata-Version: 2.4
Name: fast-boiler
Version: 0.1.3
Summary: A CLI tool to generate a FastAPI project with a Repo-Service-Controller architecture.
Author-email: Mohammad Mukhtar Mohsin <mdmukhtarmohsin@gmail.com>
License-Expression: MIT
Project-URL: Homepage, https://github.com/mdmukhtarmohsin/fast-boiler
Classifier: Programming Language :: Python :: 3
Classifier: Operating System :: OS Independent
Classifier: Framework :: FastAPI
Classifier: Topic :: Software Development :: Code Generators
Requires-Python: >=3.8
Requires-Dist: typer
Requires-Dist: rich
Requires-Dist: jinja2
